dash_mosaic/DashMosaic.py
dash_mosaic/__init__.py
dash_mosaic/_imports_.py
dash_mosaic/dash_mosaic.min.js
dash_mosaic/dash_mosaic.min.js.map
dash_mosaic/metadata.json
dash_mosaic/package-info.json
dash_mosaic_ploomber-0.0.1.dist-info/LICENSE
dash_mosaic_ploomber-0.0.1.dist-info/METADATA
dash_mosaic_ploomber-0.0.1.dist-info/WHEEL
dash_mosaic_ploomber-0.0.1.dist-info/top_level.txt
dash_mosaic_ploomber-0.0.1.dist-info/RECORD
