Metadata-Version: 2.1
Name: dash-mosaic-ploomber
Version: 0.0.1
Summary: mosaic for Dash
Author: Ploomber Inc. <contact@ploomber.io>
License: Apache-2.0
Classifier: Framework :: Dash
License-File: LICENSE
